my_img_2_text/__init__.py
my_img_2_text/my_img_2_txt.py
my_img_2_txt-1.0.1.dist-info/METADATA
my_img_2_txt-1.0.1.dist-info/WHEEL
my_img_2_txt-1.0.1.dist-info/top_level.txt
my_img_2_txt-1.0.1.dist-info/RECORD
