Metadata-Version: 2.1
Name: my_img_2_txt
Version: 1.0.1
Summary: Transform images with texts on it into a single text
Home-page: 
Author: Michelle Santos
Author-email: michellesantosvet@gmail.com
Requires-Python: >=3.8
